<!DOCTYPE PATCH  SYSTEM "http://vvvv.org/versions/vvvv45beta33.7.dtd" >
   <PATCH nodename="C:\Users\Michael\Documents\GitHub\Stimmen\subpatches\LanguageProcessing.v4p" systemname="LanguageProcessing" filename="C:\Users\Michael\Documents\GitHub\Stimmen\subpatches\LanguageProcessing.v4p">
   <BOUNDS type="Window" left="8535" top="2085" width="11715" height="8760">
   </BOUNDS>
   <PACK Name="VVVV.Packs" Version="0.2.0">
   </PACK>
   <PACK Name="addonpack" Version="33.7.0">
   </PACK>
   <NODE systemname="treeMap" filename="treeMap.v4p" nodename="subpatches\treeMap.v4p" componentmode="Hidden" id="0">
   <BOUNDS type="Node" left="1504" top="5130" width="1080" height="270">
   </BOUNDS>
   <PIN pinname="Text" visible="1" slicecount="72" values="asiatische,Kunst,Berlin,unserer,Kultur,heute,Sommerreifen,humboldtforum,dass,vier,Jahren,seine,Türen,öffnen,soll,im,stadtschloss,Berlin,Authentizität,so,ganz,leicht,geht,einem,das,wort,gar,nicht,über,Lippen,dabei,ist,es,seit,geraumer,Zeit,aller,Munde,echt,und,glaubwürdig,verlässlich,und,unverstellt,von,mir,selbst,sein,soll,aber,auch,chefin,soll,natürlich,der,Partner,sein,ganz,bei,sich,und,100,|jetzige premierminister|,|Zivilisten in Hiroshima|,|gesetzt die bombe|,|tierisch längst|,|Krieg beendet|,nachweislich,tut,Legende,Hiroshima,USA">
   </PIN>
   <PIN pinname="Value" visible="1" slicecount="72" values="0.08,0.08,0.08,0.08,0.08,0.08,0.08,0.08,0.08,0.08,0.08,0.08,0.08,0.08,0.08,0.08,0.08,0.08,0.08,0.08,0.08,0.08,0.08,0.08,0.08,0.08,0.08,0.08,0.08,0.08,0.08,0.08,0.08,0.08,0.08,0.08,0.08,0.08,0.08,0.08,0.08,0.08,0.08,0.08,0.08,0.08,0.08,0.08,0.08,0.08,0.08,0.08,0.08,0.08,0.08,0.08,0.08,0.08,0.08,0.08,0.08,0.08,0.947889,0.85983,0.853799,0.820132,0.78362,0.507451,0.451771,0.4231,1,1">
   </PIN>
   <BOUNDS type="Window" left="8745" top="1185" width="9000" height="15150">
   </BOUNDS>
   </NODE>
   <NODE systemname="wordWeight" filename="wordWeight.v4p" nodename="subpatches\wordWeight.v4p" componentmode="Hidden" id="1">
   <BOUNDS type="Node" left="1500" top="4475" width="0" height="0">
   </BOUNDS>
   <BOUNDS type="Box" left="-4192" top="-3000" width="11385" height="14950">
   </BOUNDS>
   <BOUNDS type="Window" left="2625" top="225" width="19560" height="15525">
   </BOUNDS>
   <PIN pinname="result" visible="1">
   </PIN>
   <PIN pinname="Input" visible="1">
   </PIN>
   <PIN pinname="Relevance - Input">
   </PIN>
   <PIN pinname="Entity">
   </PIN>
   <PIN pinname="Keyword">
   </PIN>
   </NODE>
   <NODE systemname="REST APIs" filename="REST APIs.v4p" nodename="subpatches\REST APIs.v4p" componentmode="Hidden" id="2" stayontop="1">
   <BOUNDS type="Node" left="3814" top="5220" width="0" height="0">
   </BOUNDS>
   <BOUNDS type="Box" left="3814" top="5220" width="14215" height="16110">
   </BOUNDS>
   <BOUNDS type="Window" left="-24330" top="900" width="23475" height="14595">
   </BOUNDS>
   <PIN pinname="Execute" slicecount="1" visible="1" values="0">
   </PIN>
   <PIN pinname="Input" visible="1">
   </PIN>
   </NODE>
   <NODE systemname="tree-tagger" filename="tree-tagger.v4p" nodename="subpatches\tree-tagger.v4p" componentmode="Hidden" id="3" stayontop="1">
   <BOUNDS type="Node" left="5284" top="5220" width="0" height="0">
   </BOUNDS>
   <BOUNDS type="Box" left="5284" top="5220" width="14215" height="9810">
   </BOUNDS>
   <BOUNDS type="Window" left="670" top="350" width="23410" height="14910">
   </BOUNDS>
   <PIN pinname="Input" visible="1" slicecount="1" values="|This is a house you are such a nice girl and I am laughing  lot|">
   </PIN>
   <PIN pinname="Execute" visible="1" slicecount="1" values="0">
   </PIN>
   <PIN pinname="Tokens" visible="1" slicecount="1" values="||">
   </PIN>
   <PIN pinname="Grammar" visible="1" slicecount="119" values="|VAFIN&tab;haben|,|PRF&tab;sich|,|ART&tab;die|,|ADJA&tab;griechisch|,|NN&tab;Regierung|,|APPR&tab;mit|,|ART&tab;die|,|NN&tab;EU|,|NN&tab;Institution|,|KON&tab;und|,|ART&tab;die|,|ADJA&tab;international|,|NN&tab;Währungsfonds|,|APPR&tab;auf|,|ART&tab;eine|,|ADJA&tab;neu|,|NN&tab;&lt;unknown&gt;|,|NN&tab;Hilfsprogramm|,|VVPP&tab;einigen|,|PAV&tab;demnach|,|VMFIN&tab;sollen|,|NE&tab;Griechenland|,|CARD&tab;86|,|NN&tab;Milliarde|,|NN&tab;Euro|,|ART&tab;eine|,|ADJA&tab;neu|,|NN&tab;Hit|,|ADJD&tab;&lt;unknown&gt;|,|VVINF&tab;bekommen|,|VMFIN&tab;müssen|,|KON&tab;aber|,|APPRART&tab;in|,|NN&tab;Gegenzug|,|APPR&tab;für|,|ART&tab;die|,|ADJA&tab;kommend|,|CARD&tab;drei|,|NN&tab;Jahr|,|ADJA&tab;neu|,|NN&tab;Sparmaßnahme|,|VVFIN&tab;durchsetzen|,|PIAT&tab;alle|,|ADJA&tab;&lt;unknown&gt;|,|VVFIN&tab;warten|,|ADJD&tab;gespannt|,|APPR&tab;auf|,|PPER&tab;sie|,|ADV&tab;ja|,|ADJD&tab;grausam|,|NN&tab;Neuigkeit|,|PIAT&tab;welche|,|NN&tab;Sparmaßnahme|,|ART&tab;die|,|APPRART&tab;in|,|NN&tab;Einzelne|,|PPOSAT&tab;sein|,|ADV&tab;aber|,|NN&tab;Finanzminister|,|NE&tab;&lt;unknown&gt;|,|NE&tab;Carlos|,|VAFIN&tab;haben|,|PRF&tab;sich|,|ADV&tab;heute|,|ADV&tab;vormittag|,|ADV&tab;erst|,|ADV&tab;einmal|,|APPR&tab;mit|,|ADJA&tab;&lt;unknown&gt;|,|NN&tab;&lt;unknown&gt;|,|ADV&tab;noch|,|VAFIN&tab;sein|,|ART&tab;die|,|NN&tab;&lt;unknown&gt;|,|ADV&tab;quasi|,|ADJD&tab;geheim|,|NN&tab;Lotus|,|VAFIN&tab;haben|,|ADV&tab;heute|,|ADJD&tab;früh|,|ADV&tab;auch|,|ADV&tab;nur|,|ADJD&tab;bedingt|,|ADJD&tab;bestätigt|,|PDS&tab;die|,|VAFIN&tab;sein|,|ART&tab;eine|,|NN&tab;Einigung|,|VVFIN&tab;geben|,|ART&tab;die|,|VVFIN&tab;warten|,|ART&tab;die|,|NN&tab;Journalist|,|VVFIN&tab;sagen|,|PPER&tab;er|,|APPRART&tab;bei|,|VVFIN&tab;vorbeigehen|,|ADV&tab;ja|,|PPER&tab;es|,|VVFIN&tab;geben|,|ADV&tab;noch|,|ART&tab;eine|,|CARD&tab;zwei|,|ADJA&tab;klein|,|NN&tab;Frage|,|ADV&tab;aber|,|PPER&tab;wir|,|VAFIN&tab;sein|,|ADJD&tab;praktisch|,|APPR&tab;durch|,|ADV&tab;so|,|NE&tab;&lt;unknown&gt;|,|ART&tab;die|,|NN&tab;Einigung|,|VVFIN&tab;fliegen|,|ADV&tab;also|,|APPR&tab;auf|,|ART&tab;die|,|NN&tab;Tisch|">
   </PIN>
   <PIN pinname="Completed" visible="1">
   </PIN>
   <PIN pinname="0: DE, 1: EN, 2: RU" visible="1" slicecount="1" values="1">
   </PIN>
   </NODE>
   <NODE systemname="EQ (String)" nodename="EQ (String)" componentmode="Hidden" id="4">
   <BOUNDS type="Node" left="5749" top="3525" width="100" height="100">
   </BOUNDS>
   <PIN pinname="Input 2" visible="1" slicecount="3" values="german,english,russian">
   </PIN>
   <PIN pinname="Input 1" visible="1" slicecount="1" values="||">
   </PIN>
   <PIN pinname="Output" visible="1">
   </PIN>
   </NODE>
   <NODE systemname="Select (String)" filename="" nodename="Select (String)" componentmode="Hidden" id="5">
   <BOUNDS type="Node" left="5284" top="4110" width="100" height="100">
   </BOUNDS>
   <PIN pinname="Input" visible="1" slicecount="3" values="german,english,russian">
   </PIN>
   <PIN pinname="Select" visible="1">
   </PIN>
   <PIN pinname="Former Slice" visible="1">
   </PIN>
   <PIN pinname="Output" visible="1">
   </PIN>
   </NODE>
   <NODE systemname="IOBox (String)" nodename="IOBox (String)" componentmode="InABox" id="6">
   <BOUNDS type="Node" left="5284" top="1500" width="100" height="100">
   </BOUNDS>
   <BOUNDS type="Box" left="5284" top="1500" width="750" height="840">
   </BOUNDS>
   <PIN pinname="Rows" slicecount="1" values="3">
   </PIN>
   <PIN pinname="Input String" slicecount="3" values="german,english,russian">
   </PIN>
   <PIN pinname="SliceCount Mode" slicecount="1" values="ColsRowsPages">
   </PIN>
   <PIN pinname="Output String" visible="1">
   </PIN>
   </NODE>
   <NODE systemname="Change (String)" nodename="Change (String)" componentmode="Hidden" id="7">
   <BOUNDS type="Node" left="6259" top="4185" width="100" height="100">
   </BOUNDS>
   <PIN pinname="Input" visible="1" slicecount="1" values="|hallo hallo|">
   </PIN>
   <PIN pinname="OnChange" visible="1">
   </PIN>
   </NODE>
   <NODE systemname="FrameDelay (Value)" filename="%VVVV%\lib\nodes\plugins\VVVV.Nodes.dll" nodename="FrameDelay (Value)" componentmode="Hidden" id="8">
   <BOUNDS type="Node" left="6259" top="4560" width="100" height="100">
   </BOUNDS>
   <PIN pinname="Input 1" visible="1">
   </PIN>
   <PIN pinname="Output 1" visible="1">
   </PIN>
   </NODE>
   <NODE nodename="IOBox (String)" componentmode="InABox" id="9" systemname="IOBox (String)">
   <BOUNDS type="Box" left="5959" top="3090" width="1005" height="240">
   </BOUNDS>
   <BOUNDS type="Node" left="5959" top="3090" width="0" height="0">
   </BOUNDS>
   <PIN pinname="Default" slicecount="1" values="||">
   </PIN>
   <PIN pinname="File Mask" slicecount="1" values="||">
   </PIN>
   <PIN pinname="Maximum Characters" slicecount="1" values="-1">
   </PIN>
   <PIN pinname="String Type" slicecount="1" values="MultiLine">
   </PIN>
   <PIN pinname="Output String" visible="1">
   </PIN>
   <PIN pinname="Input String">
   </PIN>
   </NODE>
   <NODE systemname="AvoidNIL (String)" filename="%VVVV%\lib\nodes\modules\String\AvoidNIL (String).v4p" nodename="AvoidNIL (String)" componentmode="Hidden" id="10">
   <BOUNDS type="Node" left="6289" top="3570" width="100" height="100">
   </BOUNDS>
   <PIN pinname="Input" visible="1">
   </PIN>
   <PIN pinname="Output" visible="1">
   </PIN>
   </NODE>
   <NODE id="11" systemname="IOBox (String)" componentmode="InABox" nodename="IOBox (String)">
   <PIN pinname="Descriptive Name" slicecount="1" values="Entity">
   </PIN>
   <BOUNDS type="Box" left="1500" top="500" width="750" height="240">
   </BOUNDS>
   <BOUNDS type="Node" left="1500" top="500" width="750" height="240">
   </BOUNDS>
   </NODE>
   <LINK srcnodeid="11" srcpinname="Output String" dstnodeid="1" dstpinname="Entity">
   </LINK>
   <NODE id="12" systemname="IOBox (String)" componentmode="InABox" nodename="IOBox (String)">
   <PIN pinname="Descriptive Name" slicecount="1" values="Input">
   </PIN>
   <BOUNDS type="Box" left="2400" top="500" width="750" height="240">
   </BOUNDS>
   <BOUNDS type="Node" left="2400" top="500" width="750" height="240">
   </BOUNDS>
   </NODE>
   <LINK srcnodeid="12" srcpinname="Output String" dstnodeid="1" dstpinname="Input">
   </LINK>
   <NODE id="13" systemname="IOBox (String)" componentmode="InABox" nodename="IOBox (String)">
   <PIN pinname="Descriptive Name" slicecount="1" values="Keyword">
   </PIN>
   <BOUNDS type="Box" left="3300" top="500" width="750" height="240">
   </BOUNDS>
   <BOUNDS type="Node" left="3300" top="500" width="750" height="240">
   </BOUNDS>
   </NODE>
   <LINK srcnodeid="13" srcpinname="Output String" dstnodeid="1" dstpinname="Keyword">
   </LINK>
   <NODE id="14" systemname="IOBox (String)" componentmode="InABox" nodename="IOBox (String)">
   <PIN pinname="Descriptive Name" slicecount="1" values="|Relevance - Input|">
   </PIN>
   <BOUNDS type="Box" left="4200" top="500" width="750" height="240">
   </BOUNDS>
   <BOUNDS type="Node" left="4200" top="500" width="750" height="240">
   </BOUNDS>
   </NODE>
   <LINK srcnodeid="14" srcpinname="Output String" dstnodeid="1" dstpinname="Relevance - Input">
   </LINK>
   <LINK srcnodeid="1" srcpinname="Output" dstnodeid="0" dstpinname="Value">
   </LINK>
   <LINK srcnodeid="1" srcpinname="result" dstnodeid="0" dstpinname="Text">
   </LINK>
   <LINK srcnodeid="12" srcpinname="Output String" dstnodeid="2" dstpinname="Input">
   </LINK>
   <LINK srcnodeid="8" srcpinname="Output 1" dstnodeid="2" dstpinname="Execute" linkstyle="Bezier">
   <LINKPOINT x="6259" y="5010">
   </LINKPOINT>
   <LINKPOINT x="4879" y="5010">
   </LINKPOINT>
   </LINK>
   <LINK srcnodeid="6" srcpinname="Output String" dstnodeid="5" dstpinname="Input" linkstyle="Bezier">
   <LINKPOINT x="5314" y="3225">
   </LINKPOINT>
   <LINKPOINT x="5314" y="3225">
   </LINKPOINT>
   </LINK>
   <LINK srcnodeid="4" srcpinname="Output" dstnodeid="5" dstpinname="Select" linkstyle="Bezier">
   <LINKPOINT x="5779" y="3953">
   </LINKPOINT>
   <LINKPOINT x="5779" y="3953">
   </LINKPOINT>
   </LINK>
   <NODE id="15" systemname="IOBox (String)" componentmode="InABox" nodename="IOBox (String)">
   <PIN pinname="Descriptive Name" slicecount="1" values="|Input 1 - Input String|">
   </PIN>
   <BOUNDS type="Box" left="5749" top="500" width="750" height="240">
   </BOUNDS>
   <BOUNDS type="Node" left="5749" top="500" width="750" height="240">
   </BOUNDS>
   </NODE>
   <LINK srcnodeid="15" srcpinname="Output String" dstnodeid="4" dstpinname="Input 1">
   </LINK>
   <LINK srcnodeid="9" srcpinname="Output String" dstnodeid="4" dstpinname="Input 2" linkstyle="Bezier">
   <LINKPOINT x="5974" y="3428">
   </LINKPOINT>
   <LINKPOINT x="5974" y="3428">
   </LINKPOINT>
   </LINK>
   <LINK srcnodeid="15" srcpinname="Output String" dstnodeid="9" dstpinname="Input String">
   </LINK>
   <LINK srcnodeid="10" srcpinname="Output" dstnodeid="7" dstpinname="Input" linkstyle="PolyLine">
   </LINK>
   <LINK srcnodeid="7" srcpinname="OnChange" dstnodeid="8" dstpinname="Input 1" linkstyle="Bezier">
   <LINKPOINT x="6289" y="4508">
   </LINKPOINT>
   <LINKPOINT x="6289" y="4508">
   </LINKPOINT>
   </LINK>
   <LINK srcnodeid="12" srcpinname="Output String" dstnodeid="10" dstpinname="Input">
   </LINK>
   </PATCH>